MT_PY_Performancelogging_ver2/MT_Performancelogger.py
MT_PY_Performancelogging_ver2/__init__.py
MT_PY_Performancelogging_ver2/test.py
MT_PY_Performancelogging_ver2-0.0.1.dist-info/LICENSE.txt
MT_PY_Performancelogging_ver2-0.0.1.dist-info/METADATA
MT_PY_Performancelogging_ver2-0.0.1.dist-info/WHEEL
MT_PY_Performancelogging_ver2-0.0.1.dist-info/top_level.txt
MT_PY_Performancelogging_ver2-0.0.1.dist-info/RECORD
